installer_ml/__init__.py
installer_ml/core.py
installer_ml-1.1.5.dist-info/LICENSE
installer_ml-1.1.5.dist-info/METADATA
installer_ml-1.1.5.dist-info/WHEEL
installer_ml-1.1.5.dist-info/top_level.txt
installer_ml-1.1.5.dist-info/RECORD
