Metadata-Version: 2.1
Name: installer-ml
Version: 1.1.5
Summary: Auto install and import ML/DL libraries in Python
Home-page: https://github.com/tandatnguyen89
Author: Nguyen Tan Dat
Author-email: tandatnguyen89@gmail.com
License: MIT
Classifier: Programming Language :: Python :: 3
Classifier: License :: OSI Approved :: MIT License
Classifier: Operating System :: OS Independent
Requires-Python: >=3.7
License-File: LICENSE
